qrmine/__init__.py
qrmine/__main__.py
qrmine/cluster.py
qrmine/content.py
qrmine/main.py
qrmine/mlqrmine.py
qrmine/network.py
qrmine/nlp_qrmine.py
qrmine/readfiles.py
qrmine/sentiment.py
qrmine/utils.py
qrmine/visualize.py
qrmine/resources/__init__.py
qrmine/resources/df_dominant_topic.csv
qrmine/resources/interview.txt
qrmine/resources/numeric.csv
qrmine-4.0.0.dist-info/licenses/AUTHORS.md
qrmine-4.0.0.dist-info/licenses/LICENSE.txt
qrmine-4.0.0.dist-info/METADATA
qrmine-4.0.0.dist-info/WHEEL
qrmine-4.0.0.dist-info/entry_points.txt
qrmine-4.0.0.dist-info/top_level.txt
qrmine-4.0.0.dist-info/RECORD
