Metadata-Version: 2.4
Name: qrmine
Version: 4.0.0
Summary: Qualitative Research support tools in Python!
Author-email: beapen <github@gulfdoctor.net>
License-Expression: GPL-3.0
Project-URL: Homepage, https://github.com/dermatologist/nlp-qrmine
Project-URL: Documentation, https://arxiv.org/abs/2003.13519
Platform: any
Classifier: Intended Audience :: Science/Research
Classifier: Development Status :: 4 - Beta
Classifier: Operating System :: OS Independent
Classifier: Programming Language :: Python :: 3.11
Classifier: Topic :: Scientific/Engineering :: Information Analysis
Requires-Python: <3.12,>=3.11
License-File: LICENSE.txt
License-File: AUTHORS.md
Requires-Dist: importlib-metadata; python_version < "3.8"
Requires-Dist: pandas
Requires-Dist: mlxtend
Requires-Dist: matplotlib
Requires-Dist: click
Requires-Dist: vaderSentiment
Requires-Dist: spacy
Requires-Dist: textacy
Requires-Dist: pypdf
Requires-Dist: requests
Requires-Dist: gensim
Requires-Dist: seaborn
Requires-Dist: wordcloud
Requires-Dist: tabulate
Provides-Extra: testing
Requires-Dist: setuptools; extra == "testing"
Requires-Dist: pytest; extra == "testing"
Requires-Dist: pytest-cov; extra == "testing"
Provides-Extra: dev
Requires-Dist: setuptools>=77.0.0; extra == "dev"
Requires-Dist: packaging>=24.2; extra == "dev"
Requires-Dist: setuptools_scm; extra == "dev"
Requires-Dist: pytest; extra == "dev"
Requires-Dist: pytest-cov; extra == "dev"
Requires-Dist: tox; extra == "dev"
Requires-Dist: black; extra == "dev"
Requires-Dist: recommonmark; extra == "dev"
Requires-Dist: sphinx; extra == "dev"
Requires-Dist: wheel; extra == "dev"
Requires-Dist: twine; extra == "dev"
Requires-Dist: build; extra == "dev"
Provides-Extra: ml
Requires-Dist: scikit-learn; extra == "ml"
Requires-Dist: imbalanced-learn; extra == "ml"
Requires-Dist: xgboost; extra == "ml"
Requires-Dist: torch==2.2.2; extra == "ml"
Dynamic: license-file
